iaqualink/__init__.py
iaqualink/client.py
iaqualink/const.py
iaqualink/device.py
iaqualink/exception.py
iaqualink/system.py
iaqualink/typing.py
iaqualink/version.py
iaqualink/systems/__init__.py
iaqualink/systems/iaqua/__init__.py
iaqualink/systems/iaqua/device.py
iaqualink/systems/iaqua/system.py
iaqualink-0.5.3.dist-info/METADATA
iaqualink-0.5.3.dist-info/WHEEL
iaqualink-0.5.3.dist-info/licenses/LICENSE
iaqualink-0.5.3.dist-info/RECORD
