Metadata-Version: 2.4
Name: iaqualink
Version: 0.5.3
Summary: Asynchronous library for Jandy iAqualink
Project-URL: Homepage, https://github.com/flz/iaqualink-py
Author-email: Florent Thoumie <florent@thoumie.net>
License-Expression: BSD-3-Clause
License-File: LICENSE
Keywords: iaqualink
Classifier: Development Status :: 2 - Pre-Alpha
Classifier: Intended Audience :: Developers
Classifier: License :: OSI Approved :: BSD License
Classifier: Natural Language :: English
Classifier: Programming Language :: Python :: 3.12
Classifier: Programming Language :: Python :: 3.13
Requires-Python: >=3.12
Requires-Dist: httpx[http2]>=0.27.0
Provides-Extra: dev
Requires-Dist: mypy==1.15.0; extra == 'dev'
Requires-Dist: pre-commit==4.2.0; extra == 'dev'
Requires-Dist: ruff==0.11.2; extra == 'dev'
Provides-Extra: test
Requires-Dist: coverage[toml]==7.7.1; extra == 'test'
Requires-Dist: pytest-cov==6.0.0; extra == 'test'
Requires-Dist: pytest-icdiff==0.9; extra == 'test'
Requires-Dist: pytest-sugar==1.0.0; extra == 'test'
Requires-Dist: pytest==8.3.5; extra == 'test'
Requires-Dist: respx==0.22.0; extra == 'test'
